Workbook
Name aporte: Simulator!$C$19:$C$19
Name aporte_inicial: Simulator!$C$18:$D$18
Name patrimonio: Simulator!$C$22:$C$22
Name qtd_anos: Simulator!$C$20:$C$20
Name rendimento_carteira: Simulator!$C$14:$C$14
Name salario: Simulator!$C$13:$C$13
Name sugestao_investimento: Simulator!$C$15:$C$15
Name taxa_mensal: Simulator!$C$21:$C$21

Sheet Simulator
B12: Configurações
B13: Salário | C13: 4200
B14: Rendimento Carteira | C14: 0.006
B15: Sugestão de Investimento | C15: =C13*30% -> 1260
B17: INVESTIMENTO MENSAL
B18: Aporte inicial? | C18: 150000
B19: Quanto investir por mês? | C19: 2500
B20: Por quantos anos? | C20: 10
B21: Qual a taxa de rendimento mensal? | C21: 0.01079
B22: Quanto de patrimônio vai acumular? | C22: {=FV(taxa_mensal,qtd_anos*12,aporte*-1)} -> 608210.53 | D22: {=aporte_inicial*(1+taxa_mensal)^(qtd_anos*12)+FV(taxa_mensal,qtd_anos*12,aporte*-1)} -> 1151966 | E22: 608210.53
B23: Quanto vai receber de dividendos por mês? | C23: {=patrimonio*rendimento_carteira} -> 3649.2632
B25: CENÁRIOS | D25: Dividendo
B26: Quanto em 2 anos? | C26: =FV($C$21,2*12,$C$19*-1) -> 68069.068 | D26: {=C26*rendimento_carteira} -> 408.41441
B27: Quanto em 5 anos? | C27: =FV($C$21,5*12,$C$19*-1) -> 209442.28 | D27: {=C27*rendimento_carteira} -> 1256.6537
B28: Quanto em 10 anos? | C28: =FV($C$21,10*12,$C$19*-1) -> 608210.53 | D28: {=C28*rendimento_carteira} -> 3649.2632
B29: Quanto em 20 anos? | C29: =FV($C$21,20*12,$C$19*-1) -> 2812996 | D29: {=C29*rendimento_carteira} -> 16877.976
B30: Quanto em 30 anos? | C30: =FV($C$21,30*12,$C$19*-1) -> 10805424 | D30: {=C30*rendimento_carteira} -> 64832.545
B33: Perfil | C33: AGRESSIVO
B34: VALOR A SER INVESTIDO POR MÊS | C34: 800
B36: TIPO DE FII | C36: Percentual Sugerido | D36: Valores
B37: PAPEL | C37: =VLOOKUP($C$33&"-"&B37,Folha1!A:D,4,FALSE) -> 0.5 | D37: =C37*$C$34 -> 400
B38: TIJOLO | C38: =VLOOKUP($C$33&"-"&B38,Folha1!A:D,4,FALSE) -> 0.1 | D38: =C38*$C$34 -> 80
B39: HÍBRIDOS | C39: =VLOOKUP($C$33&"-"&B39,Folha1!A:D,4,FALSE) -> 0.05 | D39: =C39*$C$34 -> 40
B40: FOFs | C40: =VLOOKUP($C$33&"-"&B40,Folha1!A:D,4,FALSE) -> 0.05 | D40: =C40*$C$34 -> 40
B41: DESENVOLVIMENTO | C41: =VLOOKUP($C$33&"-"&B41,Folha1!A:D,4,FALSE) -> 0.2 | D41: =C41*$C$34 -> 160
B42: HOTELARIAS | C42: =VLOOKUP($C$33&"-"&B42,Folha1!A:D,4,FALSE) -> 0.1 | D42: =C42*$C$34 -> 80
D43: =SUM(D37:D42) -> 800

Sheet Folha1
A3: CHAVE | B3: PERFIL | C3: TIPO DE FII | D3: %
A4: =B4&"-"&C4 -> CONSERVADOR-PAPEL | B4: CONSERVADOR | C4: PAPEL | D4: 0.3
A5: =B5&"-"&C5 -> CONSERVADOR-TIJOLO | B5: CONSERVADOR | C5: TIJOLO | D5: 0.5
A6: =B6&"-"&C6 -> CONSERVADOR-HÍBRIDOS | B6: CONSERVADOR | C6: HÍBRIDOS | D6: 0.1 | H6: %
A7: =B7&"-"&C7 -> CONSERVADOR-FOFs | B7: CONSERVADOR | C7: FOFs | D7: 0.1 | G7: MODERADO-TIJOLO | H7: =VLOOKUP(G7,$A:$D,4,FALSE) -> 0.35
A8: =B8&"-"&C8 -> CONSERVADOR-DESENVOLVIMENTO | B8: CONSERVADOR | C8: DESENVOLVIMENTO | D8: 0
A9: =B9&"-"&C9 -> CONSERVADOR-HOTELARIAS | B9: CONSERVADOR | C9: HOTELARIAS | D9: 0
A10: =B10&"-"&C10 -> MODERADO-PAPEL | B10: MODERADO | C10: PAPEL | D10: 0.32
A11: =B11&"-"&C11 -> MODERADO-TIJOLO | B11: MODERADO | C11: TIJOLO | D11: 0.35
A12: =B12&"-"&C12 -> MODERADO-HÍBRIDOS | B12: MODERADO | C12: HÍBRIDOS | D12: 0.08
A13: =B13&"-"&C13 -> MODERADO-FOFs | B13: MODERADO | C13: FOFs | D13: 0.05
A14: =B14&"-"&C14 -> MODERADO-DESENVOLVIMENTO | B14: MODERADO | C14: DESENVOLVIMENTO | D14: 0.1
A15: =B15&"-"&C15 -> MODERADO-HOTELARIAS | B15: MODERADO | C15: HOTELARIAS | D15: 0.1
A16: =B16&"-"&C16 -> AGRESSIVO-PAPEL | B16: AGRESSIVO | C16: PAPEL | D16: 0.5
A17: =B17&"-"&C17 -> AGRESSIVO-TIJOLO | B17: AGRESSIVO | C17: TIJOLO | D17: 0.1
A18: =B18&"-"&C18 -> AGRESSIVO-HÍBRIDOS | B18: AGRESSIVO | C18: HÍBRIDOS | D18: 0.05
A19: =B19&"-"&C19 -> AGRESSIVO-FOFs | B19: AGRESSIVO | C19: FOFs | D19: 0.05
... A21: =B21&"-"&C21 -> AGRESSIVO-HOTELARIAS | B21: AGRESSIVO | C21: HOTELARIAS | D21: 0.1
